README.md
setup.py
MESAPC/__init__.py
MESAPC/__main__.py
MESAPC.egg-info/PKG-INFO
MESAPC.egg-info/SOURCES.txt
MESAPC.egg-info/dependency_links.txt
MESAPC.egg-info/top_level.txt
MESAPC/_MESAPC/MESAPC.py
MESAPC/_MESAPC/MESAPC_grid.py
MESAPC/_MESAPC/Tracker.py
MESAPC/_MESAPC/__init__.py
MESAPC/_MESAPC/data_handler.py
MESAPC/_MESAPC/utils.py