Metadata-Version: 2.1
Name: MESAPC
Version: 0.0.2
Summary: Python package to calculate any grid of models with MESA
Home-page: UNKNOWN
Author: Thomas Steindl
Author-email: thomas.steindl95@gmx.at
License: UNKNOWN
Platform: UNKNOWN
Requires-Python: >=3.6
